setup.py
temp_email_validator/__init__.py
temp_email_validator.egg-info/.DS_Store
temp_email_validator.egg-info/PKG-INFO
temp_email_validator.egg-info/SOURCES.txt
temp_email_validator.egg-info/dependency_links.txt
temp_email_validator.egg-info/not-zip-safe
temp_email_validator.egg-info/top_level.txt