Metadata-Version: 1.0
Name: temp-email-validator
Version: 0.1
Summary: Temporary / Disposable Email Address Validator for Python
Home-page: http://idiotinside.com/disposable-temporary-email-address-validation/
Author: Suresh Kumar
Author-email: dsk@idiotinside.com
License: MIT
Platform: UNKNOWN
